bwmd/__init__.py
bwmd/compressor.py
bwmd/data.py
bwmd/distance.py
bwmd/partition.py
bwmd/tools.py
test/__init__.py
test/test_compressor.py
test/test_distance.py
test/test_partition.py
test/test_triplets.py
test/data/__init__.py
bwmd-0.2.2.dist-info/LICENSE.txt
bwmd-0.2.2.dist-info/METADATA
bwmd-0.2.2.dist-info/WHEEL
bwmd-0.2.2.dist-info/top_level.txt
bwmd-0.2.2.dist-info/RECORD
