Metadata-Version: 2.1
Name: bwmd
Version: 0.2.2
Summary: Fast text similarity with binary encoded word embeddings.
Home-page: https://github.com/christianj6/binarized-word-movers-distance.git
Author: Christian Johnson
Author-email: 
License: unlicensed
Platform: UNKNOWN
Classifier: Programming Language :: Python :: 3
Classifier: Programming Language :: Python :: 3.7
Requires-Dist: tensorflow (==2.6.0)
Requires-Dist: tensorflow-probability (==0.13.0)
Requires-Dist: numpy (==1.19.5)
Requires-Dist: tqdm (==4.61.2)
Requires-Dist: scipy (==1.7.1)
Requires-Dist: nltk (==3.6.2)
